{
  "objectInfo" : {
    "id" : "9oZMykYeA4Niy48g14TOwn",
    "name" : "Src_Pub_sub_tgt_pubsub",
    "type" : "SIDataflow",
    "metadata" : {
      "modelVersion" : {
        "major" : 0,
        "minor" : 0
      },
      "repoInfo" : {
        "repoHandle" : "7f0275fb-4ea3-43c4-9a1f-ccebad787171"
      },
      "contextAttributes" : [ {
        "name" : "parentId",
        "value" : "b8kDyrsShY4lNfqkaZveUz"
      }, {
        "name" : "version",
        "value" : "1"
      } ],
      "additionalInfo" : {
        "description" : null,
        "contentType" : "Binary",
        "documentState" : "COMPLETE"
      }
    }
  },
  "dataFileExtension" : "dat",
  "objectRefs" : [ {
    "id" : "6BcGQ6U7Y2QdVVJLcna2wm",
    "name" : "INsiubtu16qa01",
    "type" : "AgentGroup",
    "metadata" : {
      "modelVersion" : {
        "major" : 0,
        "minor" : 0
      },
      "repoInfo" : {
        "repoHandle" : "0101F925000000000003"
      },
      "contextAttributes" : null,
      "additionalInfo" : {
        "description" : null,
        "contentType" : "JSON",
        "documentState" : "VALID"
      }
    },
    "path" : "/SYS"
  }, {
    "id" : "5chRNcf8oywhI5Zpj2JlMq",
    "name" : "pubsub_alok",
    "type" : "Connection",
    "metadata" : {
      "modelVersion" : {
        "major" : 0,
        "minor" : 0
      },
      "repoInfo" : {
        "repoHandle" : "0101F90B000000000030"
      },
      "contextAttributes" : null,
      "additionalInfo" : {
        "description" : null,
        "contentType" : "JSON",
        "documentState" : "COMPLETE"
      }
    },
    "path" : "/SYS"
  } ]
}